{
  "type": "FeatureCollection",
  "features": [
    {
      "type": "Feature",
      "geometry": {
        "type": "Point",
        "coordinates": [
          105.641389,
          21.454167
        ]
      },
      "properties": {
        "scientificName": "Ovophis_tonkinensis",
        "latitude": 21.454167,
        "longitude": 105.641389,
        "date": "",
        "source": "PRESERVED_SPECIMEN",
        "ID": "gbif_1211744458",
        "database_recorded_species": "Ovophis tonkinensis",
        "database_recorded_subspecies": "Ovophis tonkinensis",
        "taxonomy_updated_species": "Ovophis_tonkinensis",
        "taxonomy_updated_subspecies2": "Ovophis_tonkinensis",
        "final_species": "Ovophis_tonkinensis",
        "final_subspecies": "Ovophis_tonkinensis",
        "accuracy_m": "NA",
        "country": "Vietnam",
        "locality": "VN; Vinh Phu; Tam Dao",
        "voucher": "ROM:Reptiles and Amphibians:29764",
        "issue": "OCCURRENCE_STATUS_INFERRED_FROM_INDIVIDUAL_COUNT;COORDINATE_ROUNDED;GEODETIC_DATUM_ASSUMED_WGS84;INSTITUTION_MATCH_FUZZY;INSTITUTION_COLLECTION_MISMATCH",
        "geoDist": 0,
        "phyDist": 0,
        "flag": "NA",
        "flag_detailed": "NA"
      }
    },
    {
      "type": "Feature",
      "geometry": {
        "type": "Point",
        "coordinates": [
          105.641389,
          21.454167
        ]
      },
      "properties": {
        "scientificName": "Ovophis_tonkinensis",
        "latitude": 21.454167,
        "longitude": 105.641389,
        "date": "",
        "source": "PRESERVED_SPECIMEN",
        "ID": "gbif_1211745619",
        "database_recorded_species": "Ovophis tonkinensis",
        "database_recorded_subspecies": "Ovophis tonkinensis",
        "taxonomy_updated_species": "Ovophis_tonkinensis",
        "taxonomy_updated_subspecies2": "Ovophis_tonkinensis",
        "final_species": "Ovophis_tonkinensis",
        "final_subspecies": "Ovophis_tonkinensis",
        "accuracy_m": "NA",
        "country": "Vietnam",
        "locality": "VN; Vinh Phu; Tam Dao",
        "voucher": "ROM:Reptiles and Amphibians:31082",
        "issue": "OCCURRENCE_STATUS_INFERRED_FROM_INDIVIDUAL_COUNT;COORDINATE_ROUNDED;GEODETIC_DATUM_ASSUMED_WGS84;INSTITUTION_MATCH_FUZZY;INSTITUTION_COLLECTION_MISMATCH",
        "geoDist": 0,
        "phyDist": 0,
        "flag": "NA",
        "flag_detailed": "NA"
      }
    },
    {
      "type": "Feature",
      "geometry": {
        "type": "Point",
        "coordinates": [
          105.641389,
          21.454167
        ]
      },
      "properties": {
        "scientificName": "Ovophis_tonkinensis",
        "latitude": 21.454167,
        "longitude": 105.641389,
        "date": "",
        "source": "PRESERVED_SPECIMEN",
        "ID": "gbif_1211745875",
        "database_recorded_species": "Ovophis tonkinensis",
        "database_recorded_subspecies": "Ovophis tonkinensis",
        "taxonomy_updated_species": "Ovophis_tonkinensis",
        "taxonomy_updated_subspecies2": "Ovophis_tonkinensis",
        "final_species": "Ovophis_tonkinensis",
        "final_subspecies": "Ovophis_tonkinensis",
        "accuracy_m": "NA",
        "country": "Vietnam",
        "locality": "VN; Vinh Phu; Tam Dao",
        "voucher": "ROM:Reptiles and Amphibians:29763",
        "issue": "OCCURRENCE_STATUS_INFERRED_FROM_INDIVIDUAL_COUNT;COORDINATE_ROUNDED;GEODETIC_DATUM_ASSUMED_WGS84;INSTITUTION_MATCH_FUZZY;INSTITUTION_COLLECTION_MISMATCH",
        "geoDist": 0,
        "phyDist": 0,
        "flag": "NA",
        "flag_detailed": "NA"
      }
    },
    {
      "type": "Feature",
      "geometry": {
        "type": "Point",
        "coordinates": [
          105.64378,
          21.455545
        ]
      },
      "properties": {
        "scientificName": "Ovophis_tonkinensis",
        "latitude": 21.455545,
        "longitude": 105.64378,
        "date": "",
        "source": "HUMAN_OBSERVATION",
        "ID": "gbif_1978418794",
        "database_recorded_species": "Ovophis tonkinensis",
        "database_recorded_subspecies": "Ovophis tonkinensis",
        "taxonomy_updated_species": "Ovophis_tonkinensis",
        "taxonomy_updated_subspecies2": "Ovophis_tonkinensis",
        "final_species": "Ovophis_tonkinensis",
        "final_subspecies": "Ovophis_tonkinensis",
        "accuracy_m": 444,
        "country": "Vietnam",
        "locality": "VN; V‚àÜ√≠¬¨¬©nh Ph‚Äö√†√∂‚Äö√†¬¥c; NA",
        "voucher": "iNaturalist:Observations:17410090",
        "issue": "COORDINATE_ROUNDED",
        "geoDist": 0,
        "phyDist": 0,
        "flag": "NA",
        "flag_detailed": "NA"
      }
    }
  ]
}