{
  "type": "FeatureCollection",
  "features": [
    {
      "type": "Feature",
      "geometry": {
        "type": "Point",
        "coordinates": [
          115.156898,
          4.5456
        ]
      },
      "properties": {
        "scientificName": "Trimeresurus_borneensis",
        "latitude": 4.5456,
        "longitude": 115.156898,
        "date": "",
        "source": "PRESERVED_SPECIMEN",
        "ID": "gbif_3111561471",
        "database_recorded_species": "Trimeresurus borneensis",
        "database_recorded_subspecies": "Trimeresurus borneensis",
        "taxonomy_updated_species": "Trimeresurus_borneensis",
        "taxonomy_updated_subspecies2": "Trimeresurus_borneensis",
        "final_species": "Trimeresurus_borneensis",
        "final_subspecies": "Trimeresurus_borneensis",
        "accuracy_m": "NA",
        "country": "Brunei",
        "locality": "BN; Temburong; Kuala Belalong Field Study Center (KBFSC), Ashton Trail",
        "voucher": "NCSM:Herp:105026",
        "issue": "OCCURRENCE_STATUS_INFERRED_FROM_INDIVIDUAL_COUNT;COORDINATE_ROUNDED",
        "geoDist": 0,
        "phyDist": 0,
        "flag": "NA",
        "flag_detailed": "NA"
      }
    }
  ]
}